seph/__init__.py
seph-0.0.0.dev0.dist-info/LICENSE
seph-0.0.0.dev0.dist-info/METADATA
seph-0.0.0.dev0.dist-info/WHEEL
seph-0.0.0.dev0.dist-info/top_level.txt
seph-0.0.0.dev0.dist-info/RECORD
